{
  "$schema": "https://schema.management.azure.com/schemas/2019-04-01/deploymentTemplate.json#",
  "contentVersion": "1.0.0.0",
  "parameters": {
    "workspace": {
      "type": "string"
    }
  },
  "resources": [
    {
      "type": "Microsoft.OperationalInsights/workspaces/providers/alertRules",
      "apiVersion": "2023-02-01-preview",
      "kind": "Scheduled",
      "name": "[concat(parameters('workspace'), '/Microsoft.SecurityInsights/Custom-GENMIN-AS-SNTL-003-Detectado-conectores-sin-estado-success-en-las-ultimas-12-horas-AF0CE6BD')]",
      "properties": {
        "displayName": "GENMIN AS-SNTL-003 Detectado conectores sin estado success en las últimas 12 horas",
        "description": "Detecta si algun conector ha fallado en las ultimas 12 horas",
        "severity": "Medium",
        "enabled": true,
        "query": "let lastestStatus = SentinelHealth\n| where TimeGenerated > ago(12h)\n| where OperationName == 'Data fetch status change'\n| where Status in ('Success', 'Failure')\n| parse SentinelResourceId with * '/dataConnectors/' Friendly_name\n| project TimeGenerated, SentinelResourceName, SentinelResourceId, Friendly_name, LastStatus = Status\n| summarize TimeGenerated = arg_max(TimeGenerated,*) by SentinelResourceName, SentinelResourceId, Friendly_name;\nlet nextToLastestStatus = SentinelHealth\n| where TimeGenerated > ago(12h)\n| where OperationName == 'Data fetch status change'\n| where Status in ('Success', 'Failure')\n| parse SentinelResourceId with * '/dataConnectors/' Friendly_name\n| join kind = leftanti (lastestStatus) on SentinelResourceName, SentinelResourceId, TimeGenerated\n| project TimeGenerated, SentinelResourceName, SentinelResourceId, Friendly_name, NextToLastStatus = Status\n| summarize TimeGenerated = arg_max(TimeGenerated,*) by SentinelResourceName, SentinelResourceId, Friendly_name;\nlastestStatus\n| join kind=inner (nextToLastestStatus) on SentinelResourceName, SentinelResourceId\n| where NextToLastStatus == 'Success' and LastStatus == 'Failure'\n| project TimeGenerated, Object = Friendly_name, ObjectType = SentinelResourceId, EventEndTime = NextToLastStatus",
        "queryFrequency": "PT5M",
        "queryPeriod": "PT5M",
        "triggerOperator": "GreaterThan",
        "triggerThreshold": 0,
        "suppressionEnabled": false
      }
    }
  ]
}
